confget/__init__.py
confget/__main__.py
confget/defs.py
confget/format.py
confget/py.typed
confget/backend/__init__.py
confget/backend/abstract.py
confget/backend/ini_base.py
confget/backend/ini_pyp.py
confget/backend/ini_re.py
confget-5.1.2.dist-info/METADATA
confget-5.1.2.dist-info/WHEEL
confget-5.1.2.dist-info/entry_points.txt
confget-5.1.2.dist-info/RECORD
